pifaceio.py
pifaceio-1.38.data/scripts/pifaceio-install-spidev.sh
pifaceio-1.38.dist-info/METADATA
pifaceio-1.38.dist-info/WHEEL
pifaceio-1.38.dist-info/top_level.txt
pifaceio-1.38.dist-info/RECORD
