Metadata-Version: 2.4
Name: pifaceio
Version: 1.38
Summary: Python interface to the Raspberry Pi PiFace board
Author-email: Mark Blakeney <mark.blakeney@bullet-systems.net>
License-Expression: GPL-3.0-or-later
Project-URL: Homepage, https://github.com/bulletmark/pifaceio
Keywords: piface,pifacedigitalio,spidev,raspberrypi,rpi,pi
Classifier: Programming Language :: Python :: 3
Requires-Python: >=3.6
